sqlalchemy_uow/__init__.py
sqlalchemy_uow/repository.py
sqlalchemy_uow/unit_of_work.py
sqlalchemy_uow/utils.py
sqlalchemy_uow-1.0.1.dist-info/LICENSE
sqlalchemy_uow-1.0.1.dist-info/METADATA
sqlalchemy_uow-1.0.1.dist-info/WHEEL
sqlalchemy_uow-1.0.1.dist-info/RECORD
