Metadata-Version: 2.1
Name: sqlalchemy_uow
Version: 1.0.1
Summary: Unit of Work for SQLAlchemy project
License: MIT
Author: Barbara Jesacher
Author-email: barbarajesacher@icloud.com
Requires-Python: >=3.11,<4.0
Classifier: License :: OSI Approved :: MIT License
Classifier: Programming Language :: Python :: 3
Classifier: Programming Language :: Python :: 3.11
Classifier: Programming Language :: Python :: 3.12
Requires-Dist: hydra-core (>=1.1.1,<2.0.0)
